[{"pageContent":"Index\n429\nsupport,\n \n124\nsymmetric,\n \n137\nvariance,\n \n113\nrandom\n \nwalk,\n \n154,\n \n175\nrange\n \nof\n \na\n \nrandom\n \nvariable,\n \n124\nrate\nof\n \na\n \nPoisson\n \nprocess,\n \n165\nof\n \nan\n \nexponential\n \nrandom\n \nvariable,\n \n161\nreasoning\n \nwith\n \nuncertainty,\n \n69\nSally\n \nClark\n \ncase,\n \n69\nsample\n \nmean,\n \n279\nsample\n \nspace\ncountably\n \ninfinite,\n \n13\ndiscrete,\n \n13\nuncountable,\n \n13\nsample\n \nvariance,\n \n280\nsampling\n \nwith\n \nreplacement,\n \n5\nsampling\n \nwithout\n \nreplacement,\n \n5\ncovariance,\n \n287\nexchangeability,\n \n260\nlack\n \nof\n \nindependence,\n \n58\nsemicircle\n \nlaw,\n \n92\nsequence\n \nspace,\n \n71\nsets\ncardinality,\n \n385\nde\n \nMorgan’s\n \nlaws,\n \n382\nmeasurable,\n \n28\nnumber\n \nof\n \nelements\n \nin\n \na\n \nCartesian\n \nproduct,\n388\noperations,\n \n380\nshifted\n \ngeometric\n \ndistribution,\n \n61,\n \n355\nsnake\n \neyes,\n \n173\nSt.\n \nPetersburg\n \nparadox,\n \n107\nstandard\n \nbivariate\n \nnormal\n \ndistribution,\n \n229,\n293\ncorrelation,\n \n294\nstandard\n \ndeviation,\n \n113\nstandard\n \nnormal\n \ndistribution,\n \n119\nbivariate,\n \n229\ncorrelation,\n \n294\nmean\n \nand\n \nvariance,\n \n121\nstatistic,\n \n279\nStieltjes\n \nintegral,\n \n125\nStirling’s\n \nformula,\n \n147,\n \n155\nstochastic\n \nprocess,\n \n155,\n \n363\nstopping\n \ntime,\n \n359\nsummation\n \nsymbol,\n \n399\nsunrise\n \nproblem,\n \n363\nsupport\n \nof","metadata":{"source":"C:\\Users\\chron\\Projects\\CornellGPT\\docs\\MATH_4710\\Introduction To Probability.pdf","pdf":{"version":"1.10.100","info":{"PDFFormatVersion":"1.4","IsAcroFormPresent":false,"IsXFAPresent":false,"Creator":"PDF-XChange Editor 8.0.335","Producer":"Neevia Document Converter Pro v7.2 build 131 (http://neevia.com)","CreationDate":"D:20230824190837+03'00'","ModDate":"D:20230824190837+03'00'"},"metadata":{"_metadata":{"xmp:modifydate":"2023-08-24T19:08:37+03:00","xmp:createdate":"2023-08-24T19:08:37+03:00","xmp:creatortool":"PDF-XChange Editor 8.0.335","dc:title":"Untitled"}},"totalPages":444},"loc":{"pageNumber":444,"lines":{"from":1,"to":255}}}},{"pageContent":"294\nmean\n \nand\n \nvariance,\n \n121\nstatistic,\n \n279\nStieltjes\n \nintegral,\n \n125\nStirling’s\n \nformula,\n \n147,\n \n155\nstochastic\n \nprocess,\n \n155,\n \n363\nstopping\n \ntime,\n \n359\nsummation\n \nsymbol,\n \n399\nsunrise\n \nproblem,\n \n363\nsupport\n \nof\n \nthe\n \ndistribution\n \nof\n \na\n \nrandom\nvariable,\n \n124\nsymmetric\n \nfunction,\n \n256\ntail\n \nprobability,\n \n309\nthree\n \nsigma\n \nrule,\n \n145\ntuple,\n \n385\nunbiased\n \nestimator,\n \n279,\n \n280\nuncorrelated\n \nrandom\n \nvariables,\n \n285,\n \n289\nuniform\n \ndistribution,\n \n12,\n \n92\nexpectation,\n \n106\nhigher\n \ndimensional,\n \n215\ntransformed\n \ninto\n \na\n \ndiscrete\n \ndistribution,\n195\ntransformed\n \ninto\n \na\n \nmixed\n \ndistribution,\n \n201\ntransformed\n \ninto\n \nan\n \nexponential\ndistribution,\n \n189\ntransformed\n \ninto\n \nanother\n \ncontinuous\ndistribution,\n \n196\nvariance,\n \n116\nunion\n \nof\n \nsets,\n \n381\nvariance,\n \n113,\n \n115\nlinear\n \nfunction,\n \n116\nzero,\n \n117\nVenn\n \ndiagram,\n \n381\nvolume,\n \n215\nWald’s\n \nidentity,\n \n358\nwith\n \nprobability\n \none,\n \n17,\n \n297","metadata":{"source":"C:\\Users\\chron\\Projects\\CornellGPT\\docs\\MATH_4710\\Introduction To Probability.pdf","pdf":{"version":"1.10.100","info":{"PDFFormatVersion":"1.4","IsAcroFormPresent":false,"IsXFAPresent":false,"Creator":"PDF-XChange Editor 8.0.335","Producer":"Neevia Document Converter Pro v7.2 build 131 (http://neevia.com)","CreationDate":"D:20230824190837+03'00'","ModDate":"D:20230824190837+03'00'"},"metadata":{"_metadata":{"xmp:modifydate":"2023-08-24T19:08:37+03:00","xmp:createdate":"2023-08-24T19:08:37+03:00","xmp:creatortool":"PDF-XChange Editor 8.0.335","dc:title":"Untitled"}},"totalPages":444},"loc":{"pageNumber":444,"lines":{"from":255,"to":452}}}}]